kip/__init__.py
kip/admin.py
kip/app_settings.py
kip/apps.py
kip/models.py
kip/tasks.py
kip/tests.py
kip/migrations/0001_initial.py
kip/migrations/__init__.py
django_kip-0.0.3.dist-info/LICENSE.txt
django_kip-0.0.3.dist-info/METADATA
django_kip-0.0.3.dist-info/WHEEL
django_kip-0.0.3.dist-info/top_level.txt
django_kip-0.0.3.dist-info/RECORD
